pyculas/Expression.py
pyculas/__init__.py
pyculas/formats.py
pyculas-2.0.dist-info/LICENSE.txt
pyculas-2.0.dist-info/METADATA
pyculas-2.0.dist-info/WHEEL
pyculas-2.0.dist-info/top_level.txt
pyculas-2.0.dist-info/RECORD
