Metadata-Version: 2.1
Name: pyculas
Version: 2.0
Summary: calculas python library
Home-page: https://github.com/YashIndane/pyculas
Author: Yash Indane
Author-email: yashindane46@gmail.com
License: UNKNOWN
Platform: UNKNOWN
Classifier: Programming Language :: Python :: 3
Classifier: License :: OSI Approved :: MIT License
Classifier: Operating System :: OS Independent
Requires-Python: >=3.6
